minidom_ext/DOMCompanion.py
minidom_ext/__init__.py
minidom_ext-0.0.6.dist-info/LICENSE
minidom_ext-0.0.6.dist-info/METADATA
minidom_ext-0.0.6.dist-info/WHEEL
minidom_ext-0.0.6.dist-info/top_level.txt
minidom_ext-0.0.6.dist-info/RECORD
