Metadata-Version: 2.1
Name: minidom-ext
Version: 0.0.6
Summary: Minidom extension
Home-page: https://github.com/edesmontils/Minidom_ext
Author: Emmanuel Desmontils
Author-email: emmanuel.desmontils@univ-nantes.fr
Maintainer: Emmanuel Desmontils
Maintainer-email: emmanuel.desmontils@univ-nantes.fr
License: GPL V3
Keywords: minidom XML DOM
Platform: ALL
Classifier: Topic :: Education
Classifier: Topic :: Documentation
License-File: LICENSE
Requires-Dist: lxml (>=4.5.1)
